mongoEngineLock.py
mongoEngineLock-0.1.0.dist-info/DESCRIPTION.rst
mongoEngineLock-0.1.0.dist-info/METADATA
mongoEngineLock-0.1.0.dist-info/RECORD
mongoEngineLock-0.1.0.dist-info/WHEEL
mongoEngineLock-0.1.0.dist-info/metadata.json
mongoEngineLock-0.1.0.dist-info/top_level.txt
