Metadata-Version: 2.0
Name: mongoEngineLock
Version: 0.1.0
Summary: Mongoengine pessimistic lock utility
Home-page: https://github.com/abhiTamrakar/PessimisticMongo
Author: Abhishek Tamrakar
Author-email: abhishek.tamrakar08@gmail.com
License: UNKNOWN
Platform: UNKNOWN
Classifier: Intended Audience :: Developers
Classifier: Programming Language :: Python
Classifier: Programming Language :: Python :: 2
Classifier: Programming Language :: Python :: 3
Classifier: License :: OSI Approved :: Apache Software License
Classifier: Operating System :: OS Independent
Requires-Dist: mongoengine (>=0.16.3)
Requires-Dist: pymongo (>=3.7.2)
